{
  "definitions": {},
  "$schema": "http://json-schema.org/draft-07/schema#",
  "$id": "http://eligius.com/schema/get-form-data-operation.json",
  "type": "object",
  "title": "The getFormData schema",
  "description": "Extracts all input, select, and textarea values from form element into operation data.\n\nThis operation reads form field values and returns them as an object with field names as keys.\nOnly processes form elements that are enabled and not hidden. Handles checkboxes, radio buttons,\nselect elements, textareas, and text inputs.",
  "required": [
    "systemName"
  ],
  "properties": {
    "id": {
      "$id": "#/properties/id",
      "type": "string",
      "title": "The Id Schema",
      "examples": [
        "123e4567-e89b-12d3-a456-426614174000"
      ],
      "pattern": "^[0-9a-fA-F]{8}-[0-9a-fA-F]{4}-[0-9a-fA-F]{4}-[0-9a-fA-F]{4}-[0-9a-fA-F]{12}$"
    },
    "systemName": {
      "$id": "#/properties/systemName",
      "const": "getFormData"
    }
  }
}